pyb1slayer/__init__.py
pyb1slayer/attachments.py
pyb1slayer/batch.py
pyb1slayer/connection.py
pyb1slayer/exceptions.py
pyb1slayer/models.py
pyb1slayer/ping.py
pyb1slayer/query_service.py
pyb1slayer/request.py
pyb1slayer/semantic.py
pyb1slayer/udo.py
pyb1slayer/utils.py
pyb1slayer-0.1.2.dev4.dist-info/licenses/LICENSE
pyb1slayer-0.1.2.dev4.dist-info/METADATA
pyb1slayer-0.1.2.dev4.dist-info/WHEEL
pyb1slayer-0.1.2.dev4.dist-info/top_level.txt
pyb1slayer-0.1.2.dev4.dist-info/RECORD
